dspy_builtsimple/__init__.py
dspy_builtsimple/py.typed
dspy_builtsimple/retrievers.py
dspy_builtsimple-0.1.0.dist-info/METADATA
dspy_builtsimple-0.1.0.dist-info/WHEEL
dspy_builtsimple-0.1.0.dist-info/licenses/LICENSE
dspy_builtsimple-0.1.0.dist-info/RECORD
