Metadata-Version: 2.4
Name: dspy-builtsimple
Version: 0.1.0
Summary: DSPy retriever modules for Built-Simple research APIs (PubMed, ArXiv, Wikipedia)
Project-URL: Homepage, https://github.com/built-simple/dspy-builtsimple
Project-URL: Documentation, https://github.com/built-simple/dspy-builtsimple#readme
Project-URL: Repository, https://github.com/built-simple/dspy-builtsimple
Project-URL: Issues, https://github.com/built-simple/dspy-builtsimple/issues
Author-email: Built-Simple <dev@built-simple.ai>
License-Expression: MIT
License-File: LICENSE
Keywords: arxiv,dspy,pubmed,rag,research,retrieval,scientific-literature,semantic-search,wikipedia
Classifier: Development Status :: 4 - Beta
Classifier: Intended Audience :: Developers
Classifier: Intended Audience :: Science/Research
Classifier: License :: OSI Approved :: MIT License
Classifier: Programming Language :: Python :: 3
Classifier: Programming Language :: Python :: 3.9
Classifier: Programming Language :: Python :: 3.10
Classifier: Programming Language :: Python :: 3.11
Classifier: Programming Language :: Python :: 3.12
Classifier: Topic :: Scientific/Engineering
Classifier: Topic :: Scientific/Engineering :: Artificial Intelligence
Classifier: Topic :: Scientific/Engineering :: Medical Science Apps.
Requires-Python: >=3.9
Requires-Dist: dspy>=2.4.0
Requires-Dist: httpx>=0.25.0
Provides-Extra: dev
Requires-Dist: pytest-asyncio>=0.21; extra == 'dev'
Requires-Dist: pytest>=7.0; extra == 'dev'
Requires-Dist: responses>=0.23.0; extra == 'dev'
